cmem_plugin_kubernetes/__init__.py
cmem_plugin_kubernetes/execute_task.py
cmem_plugin_kubernetes/kubernetes.svg
cmem_plugin_kubernetes-0.8.0.dist-info/METADATA
cmem_plugin_kubernetes-0.8.0.dist-info/WHEEL
cmem_plugin_kubernetes-0.8.0.dist-info/licenses/LICENSE
cmem_plugin_kubernetes-0.8.0.dist-info/RECORD
