Metadata-Version: 2.4
Name: cmem-plugin-kubernetes
Version: 0.8.0
Summary: Start processes on pods on your kubernetes cluster.
License: Apache-2.0
License-File: LICENSE
Keywords: eccenca Corporate Memory,plugin
Author: eccenca GmbH
Author-email: cmempy-developer@eccenca.com
Requires-Python: >=3.13,<4.0
Classifier: Development Status :: 4 - Beta
Classifier: Environment :: Plugins
Classifier: License :: OSI Approved :: Apache Software License
Classifier: Programming Language :: Python :: 3
Classifier: Programming Language :: Python :: 3.13
Classifier: Programming Language :: Python :: 3.14
Requires-Dist: cmem-plugin-base (>=4.15.0,<5.0.0)
Requires-Dist: kubernetes (>=33.1.0,<34.0.0)
